[{"mapx":"Z00799","name":"Xã Cán Chu Phìn","maqh":"Z027"},{"mapx":"Z00784","name":"Xã Giàng Chu Phìn","maqh":"Z027"},{"mapx":"Z00814","name":"Xã Khâu Vai","maqh":"Z027"},{"mapx":"Z00805","name":"Xã Lũng Chinh","maqh":"Z027"},{"mapx":"Z00802","name":"Xã Lũng Pù","maqh":"Z027"},{"mapx":"Z00811","name":"Xã Nậm Ban","maqh":"Z027"},{"mapx":"Z00817","name":"Xã Niêm Sơn","maqh":"Z027"},{"mapx":"Z00815","name":"Xã Niêm Tòng","maqh":"Z027"},{"mapx":"Z00781","name":"Xã Pả Vi","maqh":"Z027"},{"mapx":"Z00775","name":"Xã Pải Lủng","maqh":"Z027"},{"mapx":"Z00793","name":"Xã Sơn Vĩ","maqh":"Z027"},{"mapx":"Z00790","name":"Xã Sủng Máng","maqh":"Z027"},{"mapx":"Z00787","name":"Xã Sủng Trà","maqh":"Z027"},{"mapx":"Z00796","name":"Xã Tả Lủng","maqh":"Z027"},{"mapx":"Z00808","name":"Xã Tát Ngà","maqh":"Z027"},{"mapx":"Z00772","name":"Xã Thượng Phùng","maqh":"Z027"},{"mapx":"Z00778","name":"Xã Xín Cái","maqh":"Z027"},{"mapx":"Z00769","name":"Thị trấn Mèo Vạc","maqh":"Z027"}]