[{"mapx":"Z02658","name":"Phường Bình Minh","maqh":"Z080"},{"mapx":"Z02668","name":"Phường Bắc Cường","maqh":"Z080"},{"mapx":"Z02644","name":"Phường Cốc Lếu","maqh":"Z080"},{"mapx":"Z02650","name":"Phường Bắc Lệnh","maqh":"Z080"},{"mapx":"Z02635","name":"Phường Duyên Hải","maqh":"Z080"},{"mapx":"Z02647","name":"Phường Kim Tân","maqh":"Z080"},{"mapx":"Z02641","name":"Phường Lào Cai","maqh":"Z080"},{"mapx":"Z02671","name":"Phường Nam Cường","maqh":"Z080"},{"mapx":"Z02653","name":"Phường Pom Hán","maqh":"Z080"},{"mapx":"Z02656","name":"Phường Xuân Tăng","maqh":"Z080"},{"mapx":"Z02674","name":"Xã Cam Đường","maqh":"Z080"},{"mapx":"Z02746","name":"Xã Cốc San","maqh":"Z080"},{"mapx":"Z02662","name":"Xã Đồng Tuyển","maqh":"Z080"},{"mapx":"Z02680","name":"Xã Hợp Thành","maqh":"Z080"},{"mapx":"Z02677","name":"Xã Tả Phời","maqh":"Z080"},{"mapx":"Z02659","name":"Xã Thống Nhất","maqh":"Z080"},{"mapx":"Z02665","name":"Xã Vạn Hoà","maqh":"Z080"}]