[{"mapx":"Z07738","name":"Xã Cảnh Thụy","maqh":"Z221"},{"mapx":"Z07750","name":"Xã Đồng Phúc","maqh":"Z221"},{"mapx":"Z07747","name":"Xã Đồng Việt","maqh":"Z221"},{"mapx":"Z07735","name":"Xã Đức Giang","maqh":"Z221"},{"mapx":"Z07690","name":"Xã Hương Gián","maqh":"Z221"},{"mapx":"Z07723","name":"Xã Lãng Sơn","maqh":"Z221"},{"mapx":"Z07684","name":"Xã Lão Hộ","maqh":"Z221"},{"mapx":"Z07708","name":"Xã Nội Hoàng","maqh":"Z221"},{"mapx":"Z07702","name":"Xã Quỳnh Sơn","maqh":"Z221"},{"mapx":"Z07717","name":"Xã Tân Liễu","maqh":"Z221"},{"mapx":"Z07729","name":"Xã Tiến Dũng","maqh":"Z221"},{"mapx":"Z07711","name":"Xã Tiền Phong","maqh":"Z221"},{"mapx":"Z07720","name":"Xã Trí Yên","maqh":"Z221"},{"mapx":"Z07741","name":"Xã Tư Mại","maqh":"Z221"},{"mapx":"Z07714","name":"Xã Xuân Phú","maqh":"Z221"},{"mapx":"Z07726","name":"Xã Yên Lư","maqh":"Z221"},{"mapx":"Z07681","name":"Thị trấn Nham Biền","maqh":"Z221"},{"mapx":"Z07682","name":"Thị trấn Tân An","maqh":"Z221"}]