[{"mapx":"Z12847","name":"Xã An Tân","maqh":"Z341"},{"mapx":"Z12865","name":"Xã Dương Phúc","maqh":"Z341"},{"mapx":"Z12922","name":"Xã Hòa An","maqh":"Z341"},{"mapx":"Z12916","name":"Xã Dương Hồng  Thủy","maqh":"Z341"},{"mapx":"Z12841","name":"Xã Hồng Dũng","maqh":"Z341"},{"mapx":"Z12949","name":"Xã Mỹ Lộc","maqh":"Z341"},{"mapx":"Z12925","name":"Xã Sơn Hà","maqh":"Z341"},{"mapx":"Z12958","name":"Xã Tân Học","maqh":"Z341"},{"mapx":"Z12940","name":"Xã Thái Đô","maqh":"Z341"},{"mapx":"Z12919","name":"Xã Thái Giang","maqh":"Z341"},{"mapx":"Z12937","name":"Xã Thái Hưng","maqh":"Z341"},{"mapx":"Z12910","name":"Xã Thái Nguyên","maqh":"Z341"},{"mapx":"Z12934","name":"Xã Thái Phúc","maqh":"Z341"},{"mapx":"Z12961","name":"Xã Thái Thịnh","maqh":"Z341"},{"mapx":"Z12967","name":"Xã Thái Thọ","maqh":"Z341"},{"mapx":"Z12907","name":"Xã Thái Thượng","maqh":"Z341"},{"mapx":"Z12943","name":"Xã Thái Xuyên","maqh":"Z341"},{"mapx":"Z12964","name":"Xã Thuần Thành","maqh":"Z341"},{"mapx":"Z12871","name":"Xã Thụy Bình","maqh":"Z341"},{"mapx":"Z12874","name":"Xã Thụy Chính","maqh":"Z341"},{"mapx":"Z12877","name":"Xã Thụy Dân","maqh":"Z341"},{"mapx":"Z12892","name":"Xã Thụy Duyên","maqh":"Z341"},{"mapx":"Z12880","name":"Xã Thụy Hải","maqh":"Z341"},{"mapx":"Z12853","name":"Xã Thụy Hưng","maqh":"Z341"},{"mapx":"Z12889","name":"Xã Thụy Liên","maqh":"Z341"},{"mapx":"Z12850","name":"Xã Thụy Ninh","maqh":"Z341"},{"mapx":"Z12904","name":"Xã Thụy Phong","maqh":"Z341"},{"mapx":"Z12844","name":"Xã Thụy Quỳnh","maqh":"Z341"},{"mapx":"Z12901","name":"Xã Thụy Sơn","maqh":"Z341"},{"mapx":"Z12898","name":"Xã Thụy Thanh","maqh":"Z341"},{"mapx":"Z12868","name":"Xã Thụy Trình","maqh":"Z341"},{"mapx":"Z12832","name":"Xã Thụy Trường","maqh":"Z341"},{"mapx":"Z12859","name":"Xã Thụy Văn","maqh":"Z341"},{"mapx":"Z12856","name":"Xã Thụy Việt","maqh":"Z341"},{"mapx":"Z12862","name":"Xã Thụy Xuân","maqh":"Z341"},{"mapx":"Z12826","name":"Thị trấn Diêm Điền","maqh":"Z341"}]