[{"mapx":"Z17206","name":"Xã An Hòa","maqh":"Z421"},{"mapx":"Z17146","name":"Xã Ngọc Sơn","maqh":"Z421"},{"mapx":"Z17185","name":"Xã Quỳnh Bá","maqh":"Z421"},{"mapx":"Z17158","name":"Xã Quỳnh Bảng","maqh":"Z421"},{"mapx":"Z17122","name":"Xã Quỳnh Châu","maqh":"Z421"},{"mapx":"Z17191","name":"Xã Quỳnh Diễn","maqh":"Z421"},{"mapx":"Z17173","name":"Xã Quỳnh Đôi","maqh":"Z421"},{"mapx":"Z17197","name":"Xã Quỳnh Giang","maqh":"Z421"},{"mapx":"Z17167","name":"Xã Quỳnh Hậu","maqh":"Z421"},{"mapx":"Z17152","name":"Xã Quỳnh Hoa","maqh":"Z421"},{"mapx":"Z17179","name":"Xã Quỳnh Hồng","maqh":"Z421"},{"mapx":"Z17170","name":"Xã Quỳnh Lâm","maqh":"Z421"},{"mapx":"Z17194","name":"Xã Quỳnh Hưng","maqh":"Z421"},{"mapx":"Z17221","name":"Xã Quỳnh Long","maqh":"Z421"},{"mapx":"Z17176","name":"Xã Quỳnh Lương","maqh":"Z421"},{"mapx":"Z17188","name":"Xã Quỳnh Minh","maqh":"Z421"},{"mapx":"Z17161","name":"Xã Quỳnh Mỹ","maqh":"Z421"},{"mapx":"Z17203","name":"Xã Quỳnh Nghĩa","maqh":"Z421"},{"mapx":"Z17200","name":"Xã Quỳnh Ngọc","maqh":"Z421"},{"mapx":"Z17149","name":"Xã Quỳnh Tam","maqh":"Z421"},{"mapx":"Z17119","name":"Xã Quỳnh Tân","maqh":"Z421"},{"mapx":"Z17155","name":"Xã Quỳnh Thạch","maqh":"Z421"},{"mapx":"Z17101","name":"Xã Quỳnh Thắng","maqh":"Z421"},{"mapx":"Z17164","name":"Xã Quỳnh Thanh","maqh":"Z421"},{"mapx":"Z17215","name":"Xã Quỳnh Thọ","maqh":"Z421"},{"mapx":"Z17218","name":"Xã Quỳnh Thuận","maqh":"Z421"},{"mapx":"Z17143","name":"Xã Quỳnh Văn","maqh":"Z421"},{"mapx":"Z17182","name":"Xã Quỳnh Yên","maqh":"Z421"},{"mapx":"Z17212","name":"Xã Sơn Hải","maqh":"Z421"},{"mapx":"Z17140","name":"Xã Tân Sơn","maqh":"Z421"},{"mapx":"Z17224","name":"Xã Tân Thắng","maqh":"Z421"},{"mapx":"Z17209","name":"Xã Tiến Thủy","maqh":"Z421"},{"mapx":"Z17098","name":"Thị trấn Cầu Giát","maqh":"Z421"}]