[{"mapx":"Z21526","name":"Xã Ba Bích","maqh":"Z535"},{"mapx":"Z21511","name":"Xã Ba Cung","maqh":"Z535"},{"mapx":"Z21487","name":"Xã Ba Điền","maqh":"Z535"},{"mapx":"Z21499","name":"Xã Ba Dinh","maqh":"Z535"},{"mapx":"Z21496","name":"Xã Ba Động","maqh":"Z535"},{"mapx":"Z21500","name":"Xã Ba Giang","maqh":"Z535"},{"mapx":"Z21508","name":"Xã Ba Khâm","maqh":"Z535"},{"mapx":"Z21532","name":"Xã Ba Lế","maqh":"Z535"},{"mapx":"Z21502","name":"Xã Ba Liên","maqh":"Z535"},{"mapx":"Z21535","name":"Xã Ba Nam","maqh":"Z535"},{"mapx":"Z21505","name":"Xã Ba Ngạc","maqh":"Z535"},{"mapx":"Z21493","name":"Xã Ba Thành","maqh":"Z535"},{"mapx":"Z21523","name":"Xã Ba Tô","maqh":"Z535"},{"mapx":"Z21517","name":"Xã Ba Tiêu","maqh":"Z535"},{"mapx":"Z21520","name":"Xã Ba Trang","maqh":"Z535"},{"mapx":"Z21529","name":"Xã Ba Vì","maqh":"Z535"},{"mapx":"Z21490","name":"Xã Ba Vinh","maqh":"Z535"},{"mapx":"Z21538","name":"Xã Ba Xa","maqh":"Z535"},{"mapx":"Z21484","name":"Thị trấn Ba Tơ","maqh":"Z535"}]