[{"mapx":"Z23152","name":"Xã Bắc Ruộng","maqh":"Z599"},{"mapx":"Z23173","name":"Xã Đồng Kho","maqh":"Z599"},{"mapx":"Z23179","name":"Xã Đức Bình","maqh":"Z599"},{"mapx":"Z23170","name":"Xã Đức Phú","maqh":"Z599"},{"mapx":"Z23185","name":"Xã Đức Thuận","maqh":"Z599"},{"mapx":"Z23176","name":"Xã Gia An","maqh":"Z599"},{"mapx":"Z23182","name":"Xã Gia Huynh","maqh":"Z599"},{"mapx":"Z23164","name":"Xã Huy Khiêm","maqh":"Z599"},{"mapx":"Z23161","name":"Xã La Ngâu","maqh":"Z599"},{"mapx":"Z23167","name":"Xã Măng Tố","maqh":"Z599"},{"mapx":"Z23158","name":"Xã Nghị Đức","maqh":"Z599"},{"mapx":"Z23188","name":"Xã Suối Kiết","maqh":"Z599"},{"mapx":"Z23149","name":"Thị trấn Lạc Tánh","maqh":"Z599"}]