[{"maqh":"Z148","name":"Thành phố Hòa Bình","matt":"Z17"},{"maqh":"Z154","name":"Huyện Cao Phong","matt":"Z17"},{"maqh":"Z150","name":"Huyện Đà Bắc","matt":"Z17"},{"maqh":"Z153","name":"Huyện Kim Bôi","matt":"Z17"},{"maqh":"Z157","name":"Huyện Lạc Sơn","matt":"Z17"},{"maqh":"Z159","name":"Huyện Lạc Thủy","matt":"Z17"},{"maqh":"Z152","name":"Huyện Lương Sơn","matt":"Z17"},{"maqh":"Z156","name":"Huyện Mai Châu","matt":"Z17"},{"maqh":"Z155","name":"Huyện Tân Lạc","matt":"Z17"},{"maqh":"Z158","name":"Huyện Yên Thủy","matt":"Z17"}]